aiocells/__init__.py
aiocells/aio.py
aiocells/basic.py
aiocells/cli.py
aiocells/demo_1.py
aiocells/demo_10.py
aiocells/demo_11.py
aiocells/demo_12.py
aiocells/demo_13.py
aiocells/demo_14.py
aiocells/demo_15.py
aiocells/demo_16.py
aiocells/demo_17.py
aiocells/demo_19.py
aiocells/demo_2.py
aiocells/demo_20.py
aiocells/demo_3.py
aiocells/demo_4.py
aiocells/demo_5.py
aiocells/demo_6.py
aiocells/demo_7.py
aiocells/demo_8.py
aiocells/demo_9.py
aiocells/flow.py
aiocells/mod.py
aiocells/random_cell.py
aiocells-1.0.4.dist-info/LICENSE
aiocells-1.0.4.dist-info/METADATA
aiocells-1.0.4.dist-info/WHEEL
aiocells-1.0.4.dist-info/entry_points.txt
aiocells-1.0.4.dist-info/top_level.txt
aiocells-1.0.4.dist-info/RECORD
