Metadata-Version: 2.1
Name: aiocells
Version: 1.0.4
Summary: A package for synchronous and asynchronous dependency graph computation
Home-page: https://github.com/isbjorntrading/aiocells
Author: Anders Lindstrom
Author-email: anders@isbjorn.com.au
License: MIT
Platform: UNKNOWN
Classifier: License :: OSI Approved :: MIT License
Classifier: Programming Language :: Python :: 3
Classifier: Programming Language :: Python :: 3.8
Requires-Python: >=3.8
Requires-Dist: click (>=7.0)
Requires-Dist: klogs (>=2.0.0)
